aliasmatching/__init__.py
aliasmatching/matching.py
aliasmatching/utils/__init__.py
aliasmatching/utils/utils.py
aliasmatching-1.0.0.dist-info/LICENSE
aliasmatching-1.0.0.dist-info/METADATA
aliasmatching-1.0.0.dist-info/WHEEL
aliasmatching-1.0.0.dist-info/top_level.txt
aliasmatching-1.0.0.dist-info/RECORD
