Metadata-Version: 2.1
Name: aliasmatching
Version: 1.0.0
Summary: alias matching toolkit
Author-email: Farid <kraalfar@gmail.com>
Project-URL: Homepage, https://github.com/JetBrains-Research/am
Project-URL: Docs, https://batcore.readthedocs.io/en/latest/index.html#
Classifier: Programming Language :: Python :: 3
Classifier: License :: OSI Approved :: Apache Software License
Classifier: Operating System :: OS Independent
Requires-Python: >=3.7
License-File: LICENSE
